nav_dcat/__init__.py
nav_dcat/fields/__init__.py
nav_dcat/fields/common_fields.py
nav_dcat/models/__init__.py
nav_dcat/models/access_groups.py
nav_dcat/models/datapackage.py
nav_dcat/models/dataproduct.py
nav_dcat/models/dataset.py
nav_dcat/models/es_doc.py
nav_dcat-1.3.2.dist-info/LICENSE
nav_dcat-1.3.2.dist-info/WHEEL
nav_dcat-1.3.2.dist-info/METADATA
nav_dcat-1.3.2.dist-info/RECORD
