Metadata-Version: 2.1
Name: nav-dcat
Version: 1.3.2
Summary: 
License: MIT
Author: NAV IT dataplattform
Requires-Python: >=3.7,<4.0
Classifier: License :: OSI Approved :: MIT License
Classifier: Programming Language :: Python :: 3
Classifier: Programming Language :: Python :: 3.7
Classifier: Programming Language :: Python :: 3.8
Classifier: Programming Language :: Python :: 3.9
Requires-Dist: pydantic (>=1.8.1,<2.0.0)
Requires-Dist: pytest (>=6.2.1,<7.0.0)
